{"cameraMode":{"drawMode":0,"name":"Shaded","section":"Shading Mode"},"sceneLighting":true,"audioPlay":false,"sceneViewState":{"m_AlwaysRefresh":false,"showFog":true,"showSkybox":true,"showFlares":true,"showImageEffects":true,"showParticleSystems":true,"showVisualEffectGraphs":true,"m_FxEnabled":true},"in2DMode":false,"pivot":{"x":-59.39422607421875,"y":5.100070953369141,"z":-1.3403340578079224},"rotation":{"x":-0.2096453458070755,"y":0.03187847137451172,"z":-0.006788958329707384,"w":-0.9773041605949402},"size":2.1424341201782228,"orthographic":false}